{
    "Ar36": {
        "error": 8.960637575784751e-09,
        "error_type": "",
        "fit": "previous",
        "references": [
            {
                "exclude": false,
                "record_id": "ba-01-n-15864"
            }
        ],
        "value": 3.306102788094237e-07
    },
    "Ar37": {
        "error": 3.88685969227683e-07,
        "error_type": "",
        "fit": "previous",
        "references": [
            {
                "exclude": false,
                "record_id": "ba-01-n-15864"
            }
        ],
        "value": 8.872988653673671e-07
    },
    "Ar38": {
        "error": 3.6385909273085366e-07,
        "error_type": "",
        "fit": "previous",
        "references": [
            {
                "exclude": false,
                "record_id": "ba-01-n-15864"
            }
        ],
        "value": -6.068262846289354e-08
    },
    "Ar39": {
        "error": 3.7710045114058847e-07,
        "error_type": "",
        "fit": "previous",
        "references": [
            {
                "exclude": false,
                "record_id": "ba-01-n-15864"
            }
        ],
        "value": 1.1399368362578657e-06
    },
    "Ar40": {
        "error": 1.0576585160009304e-06,
        "error_type": "",
        "fit": "previous",
        "references": [
            {
                "exclude": false,
                "record_id": "ba-01-n-15864"
            }
        ],
        "value": 7.722149917489395e-05
    }
}