{
    "Ar36": {
        "error": 1.0069403482527026e-08,
        "error_type": "",
        "fit": "previous",
        "references": [
            {
                "exclude": false,
                "record_id": "ba-01-n-15861"
            }
        ],
        "value": 4.3415448076029445e-07
    },
    "Ar37": {
        "error": 2.284884806142144e-07,
        "error_type": "",
        "fit": "previous",
        "references": [
            {
                "exclude": false,
                "record_id": "ba-01-n-15861"
            }
        ],
        "value": 2.506027943165671e-07
    },
    "Ar38": {
        "error": 3.3966351786635426e-07,
        "error_type": "",
        "fit": "previous",
        "references": [
            {
                "exclude": false,
                "record_id": "ba-01-n-15861"
            }
        ],
        "value": 1.2430423483020042e-07
    },
    "Ar39": {
        "error": 2.904543657859289e-07,
        "error_type": "",
        "fit": "previous",
        "references": [
            {
                "exclude": false,
                "record_id": "ba-01-n-15861"
            }
        ],
        "value": 2.411592322472335e-07
    },
    "Ar40": {
        "error": 1.1147445356067096e-06,
        "error_type": "",
        "fit": "previous",
        "references": [
            {
                "exclude": false,
                "record_id": "ba-01-n-15861"
            }
        ],
        "value": 0.00011390158109880549
    }
}